eensight/__init__.py
eensight/__main__.py
eensight/hooks.py
eensight/pipeline_registry.py
eensight/pyproject.toml
eensight/settings.py
eensight/utils.py
eensight/conf/README.md
eensight/conf/base/catalog.yml
eensight/conf/base/globals.yml
eensight/conf/base/logging.yml
eensight/conf/base/parameters/predict.yml
eensight/conf/base/parameters/preprocess.yml
eensight/conf/local/.gitkeep
eensight/conf/local/credentials.yml
eensight/config/__init__.py
eensight/config/config.py
eensight/framework/__init__.py
eensight/framework/startup.py
eensight/framework/cli/__init__.py
eensight/framework/cli/help.py
eensight/framework/cli/run.py
eensight/framework/context/__init__.py
eensight/framework/context/context.py
eensight/methods/__init__.py
eensight/methods/features/__init__.py
eensight/methods/features/ordinal_encoder.py
eensight/methods/prediction/__init__.py
eensight/methods/prediction/activity.py
eensight/methods/prediction/baseline.py
eensight/methods/prediction/common.py
eensight/methods/prediction/metrics.py
eensight/methods/preprocessing/__init__.py
eensight/methods/preprocessing/adequacy.py
eensight/methods/preprocessing/alignment.py
eensight/methods/preprocessing/validation.py
eensight/pipelines/__init__.py
eensight/pipelines/adjust/__init__.py
eensight/pipelines/adjust/nodes.py
eensight/pipelines/adjust/pipeline.py
eensight/pipelines/evaluate/__init__.py
eensight/pipelines/evaluate/nodes.py
eensight/pipelines/evaluate/pipeline.py
eensight/pipelines/predict/__init__.py
eensight/pipelines/predict/nodes.py
eensight/pipelines/predict/pipeline.py
eensight/pipelines/preprocess/__init__.py
eensight/pipelines/preprocess/nodes.py
eensight/pipelines/preprocess/pipeline.py
eensight-1.0.2.dist-info/LICENSE
eensight-1.0.2.dist-info/METADATA
eensight-1.0.2.dist-info/WHEEL
eensight-1.0.2.dist-info/entry_points.txt
eensight-1.0.2.dist-info/top_level.txt
eensight-1.0.2.dist-info/RECORD
