Metadata-Version: 2.1
Name: eensight
Version: 1.0.2
Summary: A library for measurement and verification of energy efficiency projects.
Home-page: https://github.com/hebes-io/eensight
Maintainer: Sotiris Papadelis
Maintainer-email: spapadel@gmail.com
License: Apache License, Version 2.0
Keywords: measurement,verification,pipelines
Classifier: Development Status :: 4 - Beta
Classifier: License :: OSI Approved :: Apache Software License
Classifier: Programming Language :: Python :: 3
Classifier: Programming Language :: Python :: 3.7
Classifier: Programming Language :: Python :: 3.8
Classifier: Programming Language :: Python :: 3.9
Classifier: Programming Language :: Python :: 3.10
Classifier: Topic :: Software Development
Classifier: Topic :: Scientific/Engineering
Classifier: Operating System :: Microsoft :: Windows
Classifier: Operating System :: POSIX
Classifier: Operating System :: Unix
Classifier: Operating System :: MacOS
Requires-Python: >=3.7
License-File: LICENSE
Requires-Dist: catboost (>=1.1.1)
Requires-Dist: click-help-colors (>=0.9.1)
Requires-Dist: emcee (>=3.1.3)
Requires-Dist: ipywidgets (>=8.0.3)
Requires-Dist: kedro (==0.18.4)
Requires-Dist: matplotlib (>=3.6.2)
Requires-Dist: mlflow (>=2.0.1)
Requires-Dist: notebook (==6.5.2)
Requires-Dist: omegaconf (>=2.3.0)
Requires-Dist: optuna (>=3.0.4)
Requires-Dist: pandas (>=1.5.2)
Requires-Dist: scikit-learn (>=1.2.0)
Requires-Dist: scipy (>=1.8.1)
Requires-Dist: statsmodels (>=0.13.5)
Requires-Dist: tsmoothie (>=1.0.4)
